airflow/providers/asimov/_version.py
apache_airflow_providers_asimov-0.0.0.dist-info/METADATA
apache_airflow_providers_asimov-0.0.0.dist-info/WHEEL
apache_airflow_providers_asimov-0.0.0.dist-info/licenses/UNLICENSE
apache_airflow_providers_asimov-0.0.0.dist-info/RECORD
