Metadata-Version: 2.4
Name: apache-airflow-providers-asimov
Version: 0.0.0
Summary: Provider package apache-airflow-providers-asimov for Apache Airflow
Project-URL: Homepage, https://github.com/asimov-platform
Project-URL: Repository, https://github.com/asimov-platform/apache-airflow-providers-asimov
Project-URL: Changelog, https://github.com/asimov-platform/apache-airflow-providers-asimov/blob/master/CHANGES.md
Project-URL: Releases, https://github.com/asimov-platform/apache-airflow-providers-asimov/releases
Project-URL: Issues, https://github.com/asimov-platform/apache-airflow-providers-asimov/issues
Author-email: ASIMOV Protocol <support@asimov.so>
License-Expression: Unlicense
License-File: UNLICENSE
Requires-Python: >=3.9
Requires-Dist: apache-airflow>=3
